{
  "objectInfo" : {
    "id" : "a8rjJ95npKvfqXmIyxhEyc",
    "name" : "Versioned Mapping - Move",
    "type" : "DTEMPLATE",
    "metadata" : {
      "modelVersion" : {
        "major" : 0,
        "minor" : 0
      },
      "repoInfo" : {
        "repoHandle" : "010000170000000000SS"
      },
      "contextAttributes" : [ {
        "name" : "id",
        "value" : "@1"
      } ],
      "additionalInfo" : {
        "description" : "",
        "contentType" : "JSON",
        "documentState" : "INVALID"
      }
    }
  },
  "dataFileExtension" : "zip",
  "updateTime" : "2023-09-07T04:17:17.803Z",
  "objectRefs" : [ ]
}